setup.py
yhqylsh/__init__.py
yhqylsh.egg-info/PKG-INFO
yhqylsh.egg-info/SOURCES.txt
yhqylsh.egg-info/dependency_links.txt
yhqylsh.egg-info/top_level.txt