Metadata-Version: 1.0
Name: yhqylsh
Version: 0.0.1
Summary: helloKitty
Home-page: UNKNOWN
Author: chuantongmeide
Author-email: dick@foxmail.com
License: UNKNOWN
Platform: UNKNOWN
